odoo/addons/shopinvader_product_stock_assortment/README.rst
odoo/addons/shopinvader_product_stock_assortment/__init__.py
odoo/addons/shopinvader_product_stock_assortment/__manifest__.py
odoo/addons/shopinvader_product_stock_assortment/i18n/shopinvader_product_stock_assortment.pot
odoo/addons/shopinvader_product_stock_assortment/models/__init__.py
odoo/addons/shopinvader_product_stock_assortment/models/shopinvader_backend.py
odoo/addons/shopinvader_product_stock_assortment/readme/CONTRIBUTORS.rst
odoo/addons/shopinvader_product_stock_assortment/readme/CREDITS.rst
odoo/addons/shopinvader_product_stock_assortment/readme/DESCRIPTION.rst
odoo/addons/shopinvader_product_stock_assortment/static/description/index.html
odoo/addons/shopinvader_product_stock_assortment/tests/__init__.py
odoo/addons/shopinvader_product_stock_assortment/tests/test_product_auto_bind.py
odoo14_addon_shopinvader_product_stock_assortment-14.0.1.0.2.dist-info/METADATA
odoo14_addon_shopinvader_product_stock_assortment-14.0.1.0.2.dist-info/WHEEL
odoo14_addon_shopinvader_product_stock_assortment-14.0.1.0.2.dist-info/top_level.txt
odoo14_addon_shopinvader_product_stock_assortment-14.0.1.0.2.dist-info/RECORD
