Metadata-Version: 2.1
Name: odoo14-addon-shopinvader-product-stock-assortment
Version: 14.0.1.0.2
Summary: This module is used to let the Shopinvader product assortment use the stock context in Shopinvader product stock.
Home-page: https://github.com/shopinvader/odoo-shopinvader
Author: ACSONE SA/NV
License: AGPL-3
Platform: UNKNOWN
Classifier: Programming Language :: Python
Classifier: Framework :: Odoo
Classifier: Framework :: Odoo :: 14.0
Classifier: License :: OSI Approved :: GNU Affero General Public License v3
Requires-Python: >=3.6
Requires-Dist: odoo14-addon-shopinvader-assortment
Requires-Dist: odoo14-addon-shopinvader-product-stock
Requires-Dist: odoo (<14.1dev,>=14.0a)
